CHANGELOG.rst
LICENSE
MANIFEST.in
README.rst
pyproject.toml
tests.py
version.txt
txwebsocket/__init__.py
txwebsocket/txws.py
txwebsocket.egg-info/PKG-INFO
txwebsocket.egg-info/SOURCES.txt
txwebsocket.egg-info/dependency_links.txt
txwebsocket.egg-info/top_level.txt