Metadata-Version: 2.1
Name: txwebsocket
Version: 1.1.1
Summary: Twisted WebSockets support with Websocket Upgrade
Author-email: Corbin Simpson <simpsoco@osuosl.org>
License: MIT/X11
Project-URL: Homepage, https://github.com/Synerty/txwebsocket
Classifier: Programming Language :: Python :: 3.9
License-File: LICENSE
